Metadata-Version: 1.1
Name: python-tooling-example
Version: 0.0.6
Summary: Example Python package using Pytest, Sphinx, Travis, Versioneer and Github.
Home-page: https://github.com/brunobeltran/python_tooling_example
Author: Bruno Beltran
Author-email: brunobeltran0@gmail.com
License: MIT
Keywords: python tooling meta example
Platform: UNKNOWN
Classifier: Development Status :: 2 - Pre-Alpha
Classifier: Intended Audience :: Developers
Classifier: Intended Audience :: Science/Research
Classifier: License :: OSI Approved :: MIT License
Classifier: Topic :: Utilities
